Metadata-Version: 2.1
Name: django-searchable-encrypted-fields
Version: 0.2.0
Summary: Django model fields encrypted using Pycryptodome AES-256 GCM.
Home-page: https://gitlab.com/guywillett/django-searchable-encrypted-fields
Author: Guy Willett
Author-email: <guy@chamsoft.co>
Maintainer: Guy Willett
Maintainer-email: <guy@chamsoft.co>
License: MIT
Platform: UNKNOWN
Classifier: License :: OSI Approved :: MIT License
Classifier: Operating System :: OS Independent
Classifier: Programming Language :: Python :: 3.8
Classifier: Programming Language :: Python :: 3.9
Classifier: Framework :: Django
Classifier: Framework :: Django :: 3.2
Classifier: Framework :: Django :: 4.0
Classifier: Framework :: Django :: 4.1
License-File: LICENSE
